{
    "default_model": "vxpAnimaponyxlTurbo_v10Turbo.safetensors",
    "default_refiner": "None",
    "default_refiner_switch": 0.8,
    "default_loras": [
        [
            "None",
            1.0
        ],
        [
            "None",
            1.0
        ],
        [
            "None",
            1.0
        ],
        [
            "None",
            1.0
        ],
        [
            "None",
            1.0
        ]
    ],
    "default_cfg_scale": 7.0,
    "default_sample_sharpness": 2.0,
    "default_sampler": "dpmpp_2m_sde_gpu",
    "default_scheduler": "karras",
    "default_performance": "Speed",
    "default_prompt": "",
    "default_prompt_negative": "pony",
    "default_styles": [
        "Fooocus Pony"
    ],
    "default_aspect_ratio": "1024*1024",
    "checkpoint_downloads": {
        "vxpAnimaponyxlTurbo_v10Turbo.safetensors": "https://huggingface.co/Alptekinege/checkpoint/resolve/main/vxpAnimaponyxlTurbo_v10Turbo.safetensors"
    },
    "embeddings_downloads": {},
    "lora_downloads":  {},
    "previous_default_models": []
}
